lean_manufacturing/__init__.py
lean_manufacturing-0.1.4.dist-info/METADATA
lean_manufacturing-0.1.4.dist-info/WHEEL
lean_manufacturing-0.1.4.dist-info/top_level.txt
lean_manufacturing-0.1.4.dist-info/RECORD
