Metadata-Version: 2.1
Name: lean-manufacturing
Version: 0.1.4
